portia/__init__.py
portia/clarification.py
portia/clarification_handler.py
portia/cli.py
portia/cli_clarification_handler.py
portia/cloud.py
portia/common.py
portia/config.py
portia/end_user.py
portia/errors.py
portia/execution_hooks.py
portia/gemini_langsmith_wrapper.py
portia/logger.py
portia/mcp_session.py
portia/model.py
portia/plan.py
portia/plan_run.py
portia/portia.py
portia/prefixed_uuid.py
portia/storage.py
portia/token_counter.py
portia/tool.py
portia/tool_call.py
portia/tool_decorator.py
portia/tool_registry.py
portia/tool_wrapper.py
portia/_unstable/__init__.py
portia/execution_agents/__init__.py
portia/execution_agents/base_execution_agent.py
portia/execution_agents/clarification_tool.py
portia/execution_agents/context.py
portia/execution_agents/default_execution_agent.py
portia/execution_agents/execution_utils.py
portia/execution_agents/memory_extraction.py
portia/execution_agents/one_shot_agent.py
portia/execution_agents/output.py
portia/execution_agents/utils/__init__.py
portia/execution_agents/utils/final_output_summarizer.py
portia/execution_agents/utils/step_summarizer.py
portia/introspection_agents/__init__.py
portia/introspection_agents/default_introspection_agent.py
portia/introspection_agents/introspection_agent.py
portia/open_source_tools/__init__.py
portia/open_source_tools/browser_tool.py
portia/open_source_tools/calculator_tool.py
portia/open_source_tools/image_understanding_tool.py
portia/open_source_tools/llm_tool.py
portia/open_source_tools/local_file_reader_tool.py
portia/open_source_tools/local_file_writer_tool.py
portia/open_source_tools/pdf_reader_tool.py
portia/open_source_tools/registry.py
portia/open_source_tools/search_tool.py
portia/open_source_tools/weather.py
portia/planning_agents/__init__.py
portia/planning_agents/base_planning_agent.py
portia/planning_agents/context.py
portia/planning_agents/default_planning_agent.py
portia/telemetry/__init__.py
portia/telemetry/telemetry_service.py
portia/telemetry/views.py
portia_sdk_python_rfares-0.4.10.dist-info/METADATA
portia_sdk_python_rfares-0.4.10.dist-info/WHEEL
portia_sdk_python_rfares-0.4.10.dist-info/entry_points.txt
portia_sdk_python_rfares-0.4.10.dist-info/licenses/LICENSE
portia_sdk_python_rfares-0.4.10.dist-info/RECORD
