Metadata-Version: 2.4
Name: portia-sdk-python-rfares
Version: 0.4.10
Summary: Portia Labs Python SDK for building agentic workflows.
Project-URL: Homepage, https://www.portialabs.ai/
Project-URL: Repository, https://github.com/portiaAI/portia-sdk-python
Project-URL: Documentation, https://docs.portialabs.ai
Author-email: Hello <hello@portialabs.ai>
License: MIT License
License-File: LICENSE
Keywords: LLM,agentic,workflow
Classifier: Development Status :: 3 - Alpha
Requires-Python: >=3.11
Requires-Dist: anthropic<=0.55.0,>=0.41.0
Requires-Dist: click<9,>=8.1.7
Requires-Dist: instructor<2,>=1.9.0; python_version >= '3.11' and python_version < '4.0'
Requires-Dist: instructor>=1.9.0
Requires-Dist: jinja2<4,>=3.1.4
Requires-Dist: jsonref<2,>=1.1.0
Requires-Dist: langchain-anthropic<0.4,>=0.3.0; python_version >= '3.11' and python_version < '4.0'
Requires-Dist: langchain-core<0.4,>=0.3.25; python_version >= '3.11' and python_version < '4.0'
Requires-Dist: langchain-openai<0.4,>=0.3; python_version >= '3.11' and python_version < '4.0'
Requires-Dist: langchain<0.4,>=0.3.17; python_version >= '3.11' and python_version < '4.0'
Requires-Dist: langgraph<0.3,>=0.2.59; python_version >= '3.11' and python_version < '4.0'
Requires-Dist: langsmith<0.4,>=0.3.15; python_version >= '3.11' and python_version < '4.0'
Requires-Dist: loguru<0.8,>=0.7.3; python_version >= '3.11' and python_version < '4.0'
Requires-Dist: mcp<2,>=1.9.2
Requires-Dist: openpyxl<4,>=3.1.5
Requires-Dist: pandas<3,>=2.2.3
Requires-Dist: posthog~=6.0
Requires-Dist: pydantic<3,>=2.10.3
Requires-Dist: pytest-mock<4,>=3.14.0
Requires-Dist: python-dotenv<2,>=1.0.1
Requires-Dist: testcontainers[redis]>=4.10.0
Provides-Extra: all
Requires-Dist: browser-use==0.1.40; (python_version >= '3.11' and python_version < '4.0') and extra == 'all'
Requires-Dist: browserbase<2,>=1.2.0; extra == 'all'
Requires-Dist: google-genai==1.18.0; extra == 'all'
Requires-Dist: langchain-google-genai<3,>=2.0.10; (python_version >= '3.11' and python_version < '4.0') and extra == 'all'
Requires-Dist: langchain-mistralai<0.3,>=0.2.3; (python_version >= '3.11' and python_version < '4.0') and extra == 'all'
Requires-Dist: langchain-ollama<0.3,>=0.2.2; (python_version >= '3.11' and python_version < '4.0') and extra == 'all'
Requires-Dist: langchain-redis>=0.1.2; extra == 'all'
Requires-Dist: mistralai<2,>=1.2.5; extra == 'all'
Requires-Dist: playwright<2,>=1.49.0; extra == 'all'
Requires-Dist: redis<6,>=5.2.1; extra == 'all'
Provides-Extra: cache
Requires-Dist: langchain-redis>=0.1.2; extra == 'cache'
Requires-Dist: redis<6,>=5.2.1; extra == 'cache'
Provides-Extra: google
Requires-Dist: google-genai==1.18.0; extra == 'google'
Requires-Dist: langchain-google-genai<3,>=2.0.10; (python_version >= '3.11' and python_version < '4.0') and extra == 'google'
Provides-Extra: mistral
Requires-Dist: langchain-mistralai<0.3,>=0.2.3; (python_version >= '3.11' and python_version < '4.0') and extra == 'mistral'
Requires-Dist: mistralai<2,>=1.2.5; extra == 'mistral'
Provides-Extra: mistralai
Requires-Dist: langchain-mistralai<0.3,>=0.2.3; (python_version >= '3.11' and python_version < '4.0') and extra == 'mistralai'
Requires-Dist: mistralai<2,>=1.2.5; extra == 'mistralai'
Provides-Extra: ollama
Requires-Dist: langchain-ollama<0.3,>=0.2.2; (python_version >= '3.11' and python_version < '4.0') and extra == 'ollama'
Provides-Extra: tools-browser-browserbase
Requires-Dist: browser-use==0.1.40; (python_version >= '3.11' and python_version < '4.0') and extra == 'tools-browser-browserbase'
Requires-Dist: browserbase<2,>=1.2.0; extra == 'tools-browser-browserbase'
Requires-Dist: playwright<2,>=1.49.0; extra == 'tools-browser-browserbase'
Provides-Extra: tools-browser-local
Requires-Dist: browser-use==0.1.40; (python_version >= '3.11' and python_version < '4.0') and extra == 'tools-browser-local'
Requires-Dist: playwright<2,>=1.49.0; extra == 'tools-browser-local'
Provides-Extra: tools-pdf-reader
Requires-Dist: mistralai<2,>=1.2.5; extra == 'tools-pdf-reader'
